{
  "children":[
    {
      "name":"Pipeline CI",
      "children":[
        {
          "name":"Borj PDT",
          "value":1,
          "group": "good"
        },
        {
          "name":"CIB",
          "value": 1,
          "group": "good"
        },
        {
          "name":"Ebanking",
          "value": 1,
          "group": "good"
        },
        {
          "name":"Vente",
          "value": 1,
          "group": "good"
        }
      ]
    },
    {
      "name":"boss2",
      "children":[
        {
          "name":"mister_e",
          "group":"good",
          "value": 14,
          "colname":"level3"
        },
        {
          "name":"mister_f",
          "group":"good",
          "value":11,
          "colname":"level3"
        },
        {
          "name":"mister_g",
          "group":"good",
          "value":15,
          "colname":"level3"
        },
        {
          "name":"mister_h",
          "group":"good",
          "value":16,
          "colname":"level3"
        }
      ],
      "colname":"level2"
    },
    {
      "name":"boss3",
      "children":[
        {
          "name":"mister_i",
          "group":"good",
          "value":10,
          "colname":"level3"
        },
        {
          "name":"mister_j",
          "group":"good",
          "value":13,
          "colname":"level3"
        },
        {
          "name":"mister_k",
          "group":"good",
          "value":13,
          "colname":"level3"
        },
        {
          "name":"mister_l",
          "group":"good",
          "value":25,
          "colname":"level3"
        },
        {
          "name":"mister_m",
          "group":"good",
          "value":16,
          "colname":"level3"
        },
        {
          "name":"mister_n",
          "group":"good",
          "value":28,
          "colname":"level3"
        }
      ],
      "colname":"level2"
    }
  ],
  "name":"Continious Delivery"
}
